{
    "name": "ERIS Arbitrage LUNA",
    "ticker": "arbLUNA",
    "network": "LUNA",
    "tokenType": "cw20",
    "tokenDenom": null,
    "holderContract": "terra1se7rvuerys4kd2snt6vqswh9wugu49vhyzls8ymc02wl37g2p2ms5yz490",
    "stakingContract": null,
    "exponent": 6,
    "description": "Liquid Staking and Slow Burn Arbitrage Protocol built on #Terra ",
    "logoUrl": "https://raw.githubusercontent.com/cosmos/chain-registry/master/terra2/images/arbluna.svg",
    "website": "erisprotocol.com",
    "twitter": "eris_protocol",
    "telegram": "eris_protocol",
    "telegram2": null,
    "discord": null,
    "coingeckoId": null,
    "status": "active",
    "knownAddresses": [],
    "ibc": []
}
